py_axbot_utils/__init__.py
py_axbot_utils/fields.py
py_axbot_utils/geo.py
py_axbot_utils/geo_test.py
py_axbot_utils/math.py
py_axbot_utils/validators.py
py_axbot_utils/exceptions/__init__.py
py_axbot_utils/exceptions/exceptions.py
py_axbot_utils/os/__init__.py
py_axbot_utils/os/ensure.py
py_axbot_utils/os/ensure_test.py
py_axbot_utils/os/exec.py
py_axbot_utils/os/exec_test.py
py_axbot_utils/os/println.py
py_axbot_utils/os/termcolor.py
py_axbot_utils/setting_validator/__init__.py
py_axbot_utils/setting_validator/data_model.py
py_axbot_utils/setting_validator/data_model_test.py
py_axbot_utils/setting_validator/setting_validator.py
py_axbot_utils/setting_validator/setting_validator_test.py
py_axbot_utils/translations/__init__.py
py_axbot_utils/translations/translations.py
py_axbot_utils-0.1.4.dist-info/METADATA
py_axbot_utils-0.1.4.dist-info/WHEEL
py_axbot_utils-0.1.4.dist-info/top_level.txt
py_axbot_utils-0.1.4.dist-info/RECORD
