Metadata-Version: 2.4
Name: py_axbot_utils
Version: 0.1.4
Summary: Utilities for AutoXing Robotics
Home-page: https://github.com/AutoxingTech/py_axbot_utils
Author: AutoXing
Author-email: someone@autoxing.com
License: MIT
Classifier: Programming Language :: Python :: 3
Classifier: License :: OSI Approved :: MIT License
Classifier: Operating System :: OS Independent
Requires-Python: >=3.6
Dynamic: author
Dynamic: author-email
Dynamic: classifier
Dynamic: description
Dynamic: description-content-type
Dynamic: home-page
Dynamic: license
Dynamic: requires-python
Dynamic: summary
